{
  "source": "cache\\html\\STEP_Psa36.html",
  "verse_count": 12,
  "verses": [
    {
      "ref": "Ps.36.1",
      "verse_num": 1,
      "text_plain": "The transgression of the wicked saith within my heart, that there is no fear of God before his eyes.",
      "verse_html": "<span dir=\"ltr\" class=\"verse ltrDirection\"><a name=\"Ps.36.1\" class=\"verseLink\"><span class=\"verseNumber\">1</span></a><a name=\"Ps.36.1\" class=\"verseLink\"></a><span strong=\"H6588\">The transgression</span> <span strong=\"H7563\">of the wicked</span> <span morph=\"strongMorph:TH8803\" strong=\"H5002\">saith</span> <span strong=\"H7130G\">within</span> <span strong=\"H3820A\">my heart</span>, <span><em>that there is</em></span> <span strong=\"H6343\">no fear</span> <span strong=\"H0430G\">of God</span> <span strong=\"H5869A\">before his eyes</span>.</span>",
      "tokens": [
        {
          "text": "The transgression",
          "strong_norm": "H6588",
          "strong_raw": "H6588",
          "morph_norm": null,
          "morph_raw": null,
          "italics": false,
          "html_start": 25748,
          "html_end": 25793,
          "vhtml_start": 157,
          "vhtml_end": 202,
          "morph_gloss": null,
          "morph_features": null,
          "lemma": null,
          "transliteration": null,
          "pronunciation": null,
          "pos": null,
          "definition": null,
          "kjv_translation_count": null,
          "kjv_counts": null,
          "etymology": null,
          "outline": null,
          "text_start": 0,
          "text_end": 17,
          "token_id": "Ps.36.1#t0000"
        },
        {
          "text": "of the wicked",
          "strong_norm": "H7563",
          "strong_raw": "H7563",
          "morph_norm": null,
          "morph_raw": null,
          "italics": false,
          "html_start": 25794,
          "html_end": 25835,
          "vhtml_start": 203,
          "vhtml_end": 244,
          "morph_gloss": null,
          "morph_features": null,
          "lemma": null,
          "transliteration": null,
          "pronunciation": null,
          "pos": null,
          "definition": null,
          "kjv_translation_count": null,
          "kjv_counts": null,
          "etymology": null,
          "outline": null,
          "text_start": 18,
          "text_end": 31,
          "token_id": "Ps.36.1#t0001"
        },
        {
          "text": "saith",
          "strong_norm": "H5002",
          "strong_raw": "H5002",
          "morph_norm": "TH8803",
          "morph_raw": "strongMorph:TH8803",
          "italics": false,
          "html_start": 25836,
          "html_end": 25896,
          "vhtml_start": 245,
          "vhtml_end": 305,
          "morph_gloss": null,
          "morph_features": null,
          "lemma": null,
          "transliteration": null,
          "pronunciation": null,
          "pos": null,
          "definition": null,
          "kjv_translation_count": null,
          "kjv_counts": null,
          "etymology": null,
          "outline": null,
          "text_start": 32,
          "text_end": 37,
          "token_id": "Ps.36.1#t0002"
        },
        {
          "text": "within",
          "strong_norm": "H7130",
          "strong_raw": "H7130G",
          "morph_norm": null,
          "morph_raw": null,
          "italics": false,
          "html_start": 25897,
          "html_end": 25932,
          "vhtml_start": 306,
          "vhtml_end": 341,
          "morph_gloss": null,
          "morph_features": null,
          "lemma": null,
          "transliteration": null,
          "pronunciation": null,
          "pos": null,
          "definition": null,
          "kjv_translation_count": null,
          "kjv_counts": null,
          "etymology": null,
          "outline": null,
          "text_start": 38,
          "text_end": 44,
          "token_id": "Ps.36.1#t0003"
        },
        {
          "text": "my heart",
          "strong_norm": "H3820",
          "strong_raw": "H3820A",
          "morph_norm": null,
          "morph_raw": null,
          "italics": false,
          "html_start": 25933,
          "html_end": 25970,
          "vhtml_start": 342,
          "vhtml_end": 379,
          "morph_gloss": null,
          "morph_features": null,
          "lemma": null,
          "transliteration": null,
          "pronunciation": null,
          "pos": null,
          "definition": null,
          "kjv_translation_count": null,
          "kjv_counts": null,
          "etymology": null,
          "outline": null,
          "text_start": 45,
          "text_end": 53,
          "token_id": "Ps.36.1#t0004"
        },
        {
          "text": "that there is",
          "strong_norm": null,
          "strong_raw": null,
          "morph_norm": null,
          "morph_raw": null,
          "italics": true,
          "html_start": 25978,
          "html_end": 26000,
          "vhtml_start": 387,
          "vhtml_end": 409,
          "morph_gloss": null,
          "morph_features": null,
          "lemma": null,
          "transliteration": null,
          "pronunciation": null,
          "pos": null,
          "definition": null,
          "kjv_translation_count": null,
          "kjv_counts": null,
          "etymology": null,
          "outline": null,
          "text_start": 55,
          "text_end": 68,
          "token_id": "Ps.36.1#t0008"
        },
        {
          "text": "no fear",
          "strong_norm": "H6343",
          "strong_raw": "H6343",
          "morph_norm": null,
          "morph_raw": null,
          "italics": false,
          "html_start": 26008,
          "html_end": 26043,
          "vhtml_start": 417,
          "vhtml_end": 452,
          "morph_gloss": null,
          "morph_features": null,
          "lemma": null,
          "transliteration": null,
          "pronunciation": null,
          "pos": null,
          "definition": null,
          "kjv_translation_count": null,
          "kjv_counts": null,
          "etymology": null,
          "outline": null,
          "text_start": 69,
          "text_end": 76,
          "token_id": "Ps.36.1#t0005"
        },
        {
          "text": "of God",
          "strong_norm": "H0430",
          "strong_raw": "H0430G",
          "morph_norm": null,
          "morph_raw": null,
          "italics": false,
          "html_start": 26044,
          "html_end": 26079,
          "vhtml_start": 453,
          "vhtml_end": 488,
          "morph_gloss": null,
          "morph_features": null,
          "lemma": null,
          "transliteration": null,
          "pronunciation": null,
          "pos": null,
          "definition": null,
          "kjv_translation_count": null,
          "kjv_counts": null,
          "etymology": null,
          "outline": null,
          "text_start": 77,
          "text_end": 83,
          "token_id": "Ps.36.1#t0006"
        },
        {
          "text": "before his eyes",
          "strong_norm": "H5869",
          "strong_raw": "H5869A",
          "morph_norm": null,
          "morph_raw": null,
          "italics": false,
          "html_start": 26080,
          "html_end": 26124,
          "vhtml_start": 489,
          "vhtml_end": 533,
          "morph_gloss": null,
          "morph_features": null,
          "lemma": null,
          "transliteration": null,
          "pronunciation": null,
          "pos": null,
          "definition": null,
          "kjv_translation_count": null,
          "kjv_counts": null,
          "etymology": null,
          "outline": null,
          "text_start": 84,
          "text_end": 99,
          "token_id": "Ps.36.1#t0007"
        }
      ],
      "footnotes": []
    },
    {
      "ref": "Ps.36.2",
      "verse_num": 2,
      "text_plain": "For he flattereth himself in his own eyes, until his iniquity be found to be hateful.",
      "verse_html": "<span dir=\"ltr\" class=\"verse ltrDirection\"><a name=\"Ps.36.2\" class=\"verseLink\"><span class=\"verseNumber\">2</span></a><a name=\"Ps.36.2\" class=\"verseLink\"></a><span morph=\"strongMorph:TH8689\" strong=\"H2505B\">For he flattereth</span> <span strong=\"H5869A\">himself in his own eyes</span>, <span strong=\"H5771G\">until his iniquity</span> <span morph=\"strongMorph:TH8800\" strong=\"H4672\">be found</span> <span morph=\"strongMorph:TH8800\" strong=\"H8130\">to be hateful</span>. <sup class=\"note\"><a ref=\"\" xref=\"\" notetype=\"study\">▼</a><span class=\"inlineNote\"><div><a class=\"sideNote\" name=\"note-N10075\"><strong>▼</strong></a><span class=\"bold\">&nbsp;until…</span>: Heb. to find his iniquity to hate</div></span></sup></span>",
      "tokens": [
        {
          "text": "For he flattereth",
          "strong_norm": "H2505",
          "strong_raw": "H2505B",
          "morph_norm": "TH8689",
          "morph_raw": "strongMorph:TH8689",
          "italics": false,
          "html_start": 26290,
          "html_end": 26363,
          "vhtml_start": 157,
          "vhtml_end": 230,
          "morph_gloss": null,
          "morph_features": null,
          "lemma": null,
          "transliteration": null,
          "pronunciation": null,
          "pos": null,
          "definition": null,
          "kjv_translation_count": null,
          "kjv_counts": null,
          "etymology": null,
          "outline": null,
          "text_start": 0,
          "text_end": 17,
          "token_id": "Ps.36.2#t0000"
        },
        {
          "text": "himself in his own eyes",
          "strong_norm": "H5869",
          "strong_raw": "H5869A",
          "morph_norm": null,
          "morph_raw": null,
          "italics": false,
          "html_start": 26364,
          "html_end": 26416,
          "vhtml_start": 231,
          "vhtml_end": 283,
          "morph_gloss": null,
          "morph_features": null,
          "lemma": null,
          "transliteration": null,
          "pronunciation": null,
          "pos": null,
          "definition": null,
          "kjv_translation_count": null,
          "kjv_counts": null,
          "etymology": null,
          "outline": null,
          "text_start": 18,
          "text_end": 41,
          "token_id": "Ps.36.2#t0001"
        },
        {
          "text": "until his iniquity",
          "strong_norm": "H5771",
          "strong_raw": "H5771G",
          "morph_norm": null,
          "morph_raw": null,
          "italics": false,
          "html_start": 26418,
          "html_end": 26465,
          "vhtml_start": 285,
          "vhtml_end": 332,
          "morph_gloss": null,
          "morph_features": null,
          "lemma": null,
          "transliteration": null,
          "pronunciation": null,
          "pos": null,
          "definition": null,
          "kjv_translation_count": null,
          "kjv_counts": null,
          "etymology": null,
          "outline": null,
          "text_start": 43,
          "text_end": 61,
          "token_id": "Ps.36.2#t0002"
        },
        {
          "text": "be found",
          "strong_norm": "H4672",
          "strong_raw": "H4672",
          "morph_norm": "TH8800",
          "morph_raw": "strongMorph:TH8800",
          "italics": false,
          "html_start": 26466,
          "html_end": 26529,
          "vhtml_start": 333,
          "vhtml_end": 396,
          "morph_gloss": null,
          "morph_features": null,
          "lemma": null,
          "transliteration": null,
          "pronunciation": null,
          "pos": null,
          "definition": null,
          "kjv_translation_count": null,
          "kjv_counts": null,
          "etymology": null,
          "outline": null,
          "text_start": 62,
          "text_end": 70,
          "token_id": "Ps.36.2#t0003"
        },
        {
          "text": "to be hateful",
          "strong_norm": "H8130",
          "strong_raw": "H8130",
          "morph_norm": "TH8800",
          "morph_raw": "strongMorph:TH8800",
          "italics": false,
          "html_start": 26530,
          "html_end": 26598,
          "vhtml_start": 397,
          "vhtml_end": 465,
          "morph_gloss": null,
          "morph_features": null,
          "lemma": null,
          "transliteration": null,
          "pronunciation": null,
          "pos": null,
          "definition": null,
          "kjv_translation_count": null,
          "kjv_counts": null,
          "etymology": null,
          "outline": null,
          "text_start": 71,
          "text_end": 84,
          "token_id": "Ps.36.2#t0004"
        }
      ],
      "footnotes": [
        {
          "marker": "▼",
          "notetype": "study",
          "ref_attr": null,
          "xref_attr": null,
          "body_text": "▼ until…: Heb. to find his iniquity to hate",
          "body_html": "<span class=\"inlineNote\"><div><a class=\"sideNote\" name=\"note-N10075\"><strong>▼</strong></a><span class=\"bold\">&nbsp;until…</span>: Heb. to find his iniquity to hate</div></span>"
        }
      ]
    },
    {
      "ref": "Ps.36.3",
      "verse_num": 3,
      "text_plain": "The words of his mouth are iniquity and deceit: he hath left off to be wise, and to do good.",
      "verse_html": "<span dir=\"ltr\" class=\"verse ltrDirection\"><a name=\"Ps.36.3\" class=\"verseLink\"><span class=\"verseNumber\">3</span></a><a name=\"Ps.36.3\" class=\"verseLink\"></a><span strong=\"H1697G\">The words</span> <span strong=\"H6310G\">of his mouth</span> <span><em>are</em></span> <span strong=\"H0205G\">iniquity</span> <span strong=\"H4820\">and deceit</span>: <span morph=\"strongMorph:TH8804\" strong=\"H2308\">he hath left off</span> <span morph=\"strongMorph:TH8687\" strong=\"H7919A\">to be wise</span>, <span><em>and</em></span> <span morph=\"strongMorph:TH8687\" strong=\"H3190\">to do good</span>.</span>",
      "tokens": [
        {
          "text": "The words",
          "strong_norm": "H1697",
          "strong_raw": "H1697G",
          "morph_norm": null,
          "morph_raw": null,
          "italics": false,
          "html_start": 27006,
          "html_end": 27044,
          "vhtml_start": 157,
          "vhtml_end": 195,
          "morph_gloss": null,
          "morph_features": null,
          "lemma": null,
          "transliteration": null,
          "pronunciation": null,
          "pos": null,
          "definition": null,
          "kjv_translation_count": null,
          "kjv_counts": null,
          "etymology": null,
          "outline": null,
          "text_start": 0,
          "text_end": 9,
          "token_id": "Ps.36.3#t0000"
        },
        {
          "text": "of his mouth",
          "strong_norm": "H6310",
          "strong_raw": "H6310G",
          "morph_norm": null,
          "morph_raw": null,
          "italics": false,
          "html_start": 27045,
          "html_end": 27086,
          "vhtml_start": 196,
          "vhtml_end": 237,
          "morph_gloss": null,
          "morph_features": null,
          "lemma": null,
          "transliteration": null,
          "pronunciation": null,
          "pos": null,
          "definition": null,
          "kjv_translation_count": null,
          "kjv_counts": null,
          "etymology": null,
          "outline": null,
          "text_start": 10,
          "text_end": 22,
          "token_id": "Ps.36.3#t0001"
        },
        {
          "text": "are",
          "strong_norm": null,
          "strong_raw": null,
          "morph_norm": null,
          "morph_raw": null,
          "italics": true,
          "html_start": 29102,
          "html_end": 29114,
          "vhtml_start": 244,
          "vhtml_end": 256,
          "morph_gloss": null,
          "morph_features": null,
          "lemma": null,
          "transliteration": null,
          "pronunciation": null,
          "pos": null,
          "definition": null,
          "kjv_translation_count": null,
          "kjv_counts": null,
          "etymology": null,
          "outline": null,
          "text_start": 23,
          "text_end": 26,
          "token_id": "Ps.36.3#t0007"
        },
        {
          "text": "iniquity",
          "strong_norm": "H0205",
          "strong_raw": "H0205G",
          "morph_norm": null,
          "morph_raw": null,
          "italics": false,
          "html_start": 27113,
          "html_end": 27150,
          "vhtml_start": 264,
          "vhtml_end": 301,
          "morph_gloss": null,
          "morph_features": null,
          "lemma": null,
          "transliteration": null,
          "pronunciation": null,
          "pos": null,
          "definition": null,
          "kjv_translation_count": null,
          "kjv_counts": null,
          "etymology": null,
          "outline": null,
          "text_start": 27,
          "text_end": 35,
          "token_id": "Ps.36.3#t0002"
        },
        {
          "text": "and deceit",
          "strong_norm": "H4820",
          "strong_raw": "H4820",
          "morph_norm": null,
          "morph_raw": null,
          "italics": false,
          "html_start": 27151,
          "html_end": 27189,
          "vhtml_start": 302,
          "vhtml_end": 340,
          "morph_gloss": null,
          "morph_features": null,
          "lemma": null,
          "transliteration": null,
          "pronunciation": null,
          "pos": null,
          "definition": null,
          "kjv_translation_count": null,
          "kjv_counts": null,
          "etymology": null,
          "outline": null,
          "text_start": 36,
          "text_end": 46,
          "token_id": "Ps.36.3#t0003"
        },
        {
          "text": "he hath left off",
          "strong_norm": "H2308",
          "strong_raw": "H2308",
          "morph_norm": "TH8804",
          "morph_raw": "strongMorph:TH8804",
          "italics": false,
          "html_start": 27191,
          "html_end": 27262,
          "vhtml_start": 342,
          "vhtml_end": 413,
          "morph_gloss": null,
          "morph_features": null,
          "lemma": null,
          "transliteration": null,
          "pronunciation": null,
          "pos": null,
          "definition": null,
          "kjv_translation_count": null,
          "kjv_counts": null,
          "etymology": null,
          "outline": null,
          "text_start": 48,
          "text_end": 64,
          "token_id": "Ps.36.3#t0004"
        },
        {
          "text": "to be wise",
          "strong_norm": "H7919",
          "strong_raw": "H7919A",
          "morph_norm": "TH8687",
          "morph_raw": "strongMorph:TH8687",
          "italics": false,
          "html_start": 27263,
          "html_end": 27329,
          "vhtml_start": 414,
          "vhtml_end": 480,
          "morph_gloss": null,
          "morph_features": null,
          "lemma": null,
          "transliteration": null,
          "pronunciation": null,
          "pos": null,
          "definition": null,
          "kjv_translation_count": null,
          "kjv_counts": null,
          "etymology": null,
          "outline": null,
          "text_start": 65,
          "text_end": 75,
          "token_id": "Ps.36.3#t0005"
        },
        {
          "text": "and",
          "strong_norm": null,
          "strong_raw": null,
          "morph_norm": null,
          "morph_raw": null,
          "italics": true,
          "html_start": 27337,
          "html_end": 27349,
          "vhtml_start": 488,
          "vhtml_end": 500,
          "morph_gloss": null,
          "morph_features": null,
          "lemma": null,
          "transliteration": null,
          "pronunciation": null,
          "pos": null,
          "definition": null,
          "kjv_translation_count": null,
          "kjv_counts": null,
          "etymology": null,
          "outline": null,
          "text_start": 77,
          "text_end": 80,
          "token_id": "Ps.36.3#t0008"
        },
        {
          "text": "to do good",
          "strong_norm": "H3190",
          "strong_raw": "H3190",
          "morph_norm": "TH8687",
          "morph_raw": "strongMorph:TH8687",
          "italics": false,
          "html_start": 27357,
          "html_end": 27422,
          "vhtml_start": 508,
          "vhtml_end": 573,
          "morph_gloss": null,
          "morph_features": null,
          "lemma": null,
          "transliteration": null,
          "pronunciation": null,
          "pos": null,
          "definition": null,
          "kjv_translation_count": null,
          "kjv_counts": null,
          "etymology": null,
          "outline": null,
          "text_start": 81,
          "text_end": 91,
          "token_id": "Ps.36.3#t0006"
        }
      ],
      "footnotes": []
    },
    {
      "ref": "Ps.36.4",
      "verse_num": 4,
      "text_plain": "He deviseth mischief upon his bed; he setteth himself in a way that is not good; he abhorreth not evil.",
      "verse_html": "<span dir=\"ltr\" class=\"verse ltrDirection\"><a name=\"Ps.36.4\" class=\"verseLink\"><span class=\"verseNumber\">4</span></a><a name=\"Ps.36.4\" class=\"verseLink\"></a><span morph=\"strongMorph:TH8799\" strong=\"H2803I\">He deviseth</span> <span strong=\"H0205G\">mischief</span> <span strong=\"H4904\">upon his bed</span>; <span morph=\"strongMorph:TH8691\" strong=\"H3320\">he setteth</span> <span strong=\"H1870G\">himself in a way</span> <span><em>that is</em></span> <span strong=\"H2896A\">not good</span>; <span morph=\"strongMorph:TH8799\" strong=\"H3988A\">he abhorreth</span> <span strong=\"H7451B\">not evil</span>. <sup class=\"note\"><a ref=\"\" xref=\"\" notetype=\"study\">▼</a><span class=\"inlineNote\"><div><a class=\"sideNote\" name=\"note-N100CF\"><strong>▼</strong></a><span class=\"bold\">&nbsp;mischief</span>: or, vanity</div></span></sup></span>",
      "tokens": [
        {
          "text": "He deviseth",
          "strong_norm": "H2803",
          "strong_raw": "H2803I",
          "morph_norm": "TH8799",
          "morph_raw": "strongMorph:TH8799",
          "italics": false,
          "html_start": 27588,
          "html_end": 27655,
          "vhtml_start": 157,
          "vhtml_end": 224,
          "morph_gloss": null,
          "morph_features": null,
          "lemma": null,
          "transliteration": null,
          "pronunciation": null,
          "pos": null,
          "definition": null,
          "kjv_translation_count": null,
          "kjv_counts": null,
          "etymology": null,
          "outline": null,
          "text_start": 0,
          "text_end": 11,
          "token_id": "Ps.36.4#t0000"
        },
        {
          "text": "mischief",
          "strong_norm": "H0205",
          "strong_raw": "H0205G",
          "morph_norm": null,
          "morph_raw": null,
          "italics": false,
          "html_start": 27656,
          "html_end": 27693,
          "vhtml_start": 225,
          "vhtml_end": 262,
          "morph_gloss": null,
          "morph_features": null,
          "lemma": null,
          "transliteration": null,
          "pronunciation": null,
          "pos": null,
          "definition": null,
          "kjv_translation_count": null,
          "kjv_counts": null,
          "etymology": null,
          "outline": null,
          "text_start": 12,
          "text_end": 20,
          "token_id": "Ps.36.4#t0001"
        },
        {
          "text": "upon his bed",
          "strong_norm": "H4904",
          "strong_raw": "H4904",
          "morph_norm": null,
          "morph_raw": null,
          "italics": false,
          "html_start": 27694,
          "html_end": 27734,
          "vhtml_start": 263,
          "vhtml_end": 303,
          "morph_gloss": null,
          "morph_features": null,
          "lemma": null,
          "transliteration": null,
          "pronunciation": null,
          "pos": null,
          "definition": null,
          "kjv_translation_count": null,
          "kjv_counts": null,
          "etymology": null,
          "outline": null,
          "text_start": 21,
          "text_end": 33,
          "token_id": "Ps.36.4#t0002"
        },
        {
          "text": "he setteth",
          "strong_norm": "H3320",
          "strong_raw": "H3320",
          "morph_norm": "TH8691",
          "morph_raw": "strongMorph:TH8691",
          "italics": false,
          "html_start": 27736,
          "html_end": 27801,
          "vhtml_start": 305,
          "vhtml_end": 370,
          "morph_gloss": null,
          "morph_features": null,
          "lemma": null,
          "transliteration": null,
          "pronunciation": null,
          "pos": null,
          "definition": null,
          "kjv_translation_count": null,
          "kjv_counts": null,
          "etymology": null,
          "outline": null,
          "text_start": 35,
          "text_end": 45,
          "token_id": "Ps.36.4#t0003"
        },
        {
          "text": "himself in a way",
          "strong_norm": "H1870",
          "strong_raw": "H1870G",
          "morph_norm": null,
          "morph_raw": null,
          "italics": false,
          "html_start": 27802,
          "html_end": 27847,
          "vhtml_start": 371,
          "vhtml_end": 416,
          "morph_gloss": null,
          "morph_features": null,
          "lemma": null,
          "transliteration": null,
          "pronunciation": null,
          "pos": null,
          "definition": null,
          "kjv_translation_count": null,
          "kjv_counts": null,
          "etymology": null,
          "outline": null,
          "text_start": 46,
          "text_end": 62,
          "token_id": "Ps.36.4#t0004"
        },
        {
          "text": "that is",
          "strong_norm": null,
          "strong_raw": null,
          "morph_norm": null,
          "morph_raw": null,
          "italics": true,
          "html_start": 27854,
          "html_end": 27870,
          "vhtml_start": 423,
          "vhtml_end": 439,
          "morph_gloss": null,
          "morph_features": null,
          "lemma": null,
          "transliteration": null,
          "pronunciation": null,
          "pos": null,
          "definition": null,
          "kjv_translation_count": null,
          "kjv_counts": null,
          "etymology": null,
          "outline": null,
          "text_start": 63,
          "text_end": 70,
          "token_id": "Ps.36.4#t0008"
        },
        {
          "text": "not good",
          "strong_norm": "H2896",
          "strong_raw": "H2896A",
          "morph_norm": null,
          "morph_raw": null,
          "italics": false,
          "html_start": 27878,
          "html_end": 27915,
          "vhtml_start": 447,
          "vhtml_end": 484,
          "morph_gloss": null,
          "morph_features": null,
          "lemma": null,
          "transliteration": null,
          "pronunciation": null,
          "pos": null,
          "definition": null,
          "kjv_translation_count": null,
          "kjv_counts": null,
          "etymology": null,
          "outline": null,
          "text_start": 71,
          "text_end": 79,
          "token_id": "Ps.36.4#t0005"
        },
        {
          "text": "he abhorreth",
          "strong_norm": "H3988",
          "strong_raw": "H3988A",
          "morph_norm": "TH8799",
          "morph_raw": "strongMorph:TH8799",
          "italics": false,
          "html_start": 27917,
          "html_end": 27985,
          "vhtml_start": 486,
          "vhtml_end": 554,
          "morph_gloss": null,
          "morph_features": null,
          "lemma": null,
          "transliteration": null,
          "pronunciation": null,
          "pos": null,
          "definition": null,
          "kjv_translation_count": null,
          "kjv_counts": null,
          "etymology": null,
          "outline": null,
          "text_start": 81,
          "text_end": 93,
          "token_id": "Ps.36.4#t0006"
        },
        {
          "text": "not evil",
          "strong_norm": "H7451",
          "strong_raw": "H7451B",
          "morph_norm": null,
          "morph_raw": null,
          "italics": false,
          "html_start": 27986,
          "html_end": 28023,
          "vhtml_start": 555,
          "vhtml_end": 592,
          "morph_gloss": null,
          "morph_features": null,
          "lemma": null,
          "transliteration": null,
          "pronunciation": null,
          "pos": null,
          "definition": null,
          "kjv_translation_count": null,
          "kjv_counts": null,
          "etymology": null,
          "outline": null,
          "text_start": 94,
          "text_end": 102,
          "token_id": "Ps.36.4#t0007"
        }
      ],
      "footnotes": [
        {
          "marker": "▼",
          "notetype": "study",
          "ref_attr": null,
          "xref_attr": null,
          "body_text": "▼ mischief: or, vanity",
          "body_html": "<span class=\"inlineNote\"><div><a class=\"sideNote\" name=\"note-N100CF\"><strong>▼</strong></a><span class=\"bold\">&nbsp;mischief</span>: or, vanity</div></span>"
        }
      ]
    },
    {
      "ref": "Ps.36.5",
      "verse_num": 5,
      "text_plain": "Thy mercy, O Lord, is in the heavens; and thy faithfulness reacheth unto the clouds.",
      "verse_html": "<span dir=\"ltr\" class=\"verse ltrDirection\"><a name=\"Ps.36.5\" class=\"verseLink\"><span class=\"verseNumber\">5</span></a><a name=\"Ps.36.5\" class=\"verseLink\"></a><span strong=\"H2617A\">Thy mercy</span>, <span strong=\"H3068G\">O <span class=\"small-caps\">Lord</span></span>, <span><em>is</em></span> <span strong=\"H8064\">in the heavens</span>; <span><em>and</em></span> <span strong=\"H0530\">thy faithfulness</span> <span><em>reacheth</em></span> <span strong=\"H7834\">unto the clouds</span>.</span>",
      "tokens": [
        {
          "text": "Thy mercy",
          "strong_norm": "H2617",
          "strong_raw": "H2617A",
          "morph_norm": null,
          "morph_raw": null,
          "italics": false,
          "html_start": 28410,
          "html_end": 28448,
          "vhtml_start": 157,
          "vhtml_end": 195,
          "morph_gloss": null,
          "morph_features": null,
          "lemma": null,
          "transliteration": null,
          "pronunciation": null,
          "pos": null,
          "definition": null,
          "kjv_translation_count": null,
          "kjv_counts": null,
          "etymology": null,
          "outline": null,
          "text_start": 0,
          "text_end": 9,
          "token_id": "Ps.36.5#t0000"
        },
        {
          "text": "O Lord",
          "strong_norm": "H3068",
          "strong_raw": "H3068G",
          "morph_norm": null,
          "morph_raw": null,
          "italics": false,
          "html_start": 28450,
          "html_end": 28517,
          "vhtml_start": 197,
          "vhtml_end": 264,
          "morph_gloss": null,
          "morph_features": null,
          "lemma": null,
          "transliteration": null,
          "pronunciation": null,
          "pos": null,
          "definition": null,
          "kjv_translation_count": null,
          "kjv_counts": null,
          "etymology": null,
          "outline": null,
          "text_start": 11,
          "text_end": 17,
          "token_id": "Ps.36.5#t0001"
        },
        {
          "text": "is",
          "strong_norm": null,
          "strong_raw": null,
          "morph_norm": null,
          "morph_raw": null,
          "italics": true,
          "html_start": 28951,
          "html_end": 28962,
          "vhtml_start": 272,
          "vhtml_end": 283,
          "morph_gloss": null,
          "morph_features": null,
          "lemma": null,
          "transliteration": null,
          "pronunciation": null,
          "pos": null,
          "definition": null,
          "kjv_translation_count": null,
          "kjv_counts": null,
          "etymology": null,
          "outline": null,
          "text_start": 19,
          "text_end": 21,
          "token_id": "Ps.36.5#t0005"
        },
        {
          "text": "in the heavens",
          "strong_norm": "H8064",
          "strong_raw": "H8064",
          "morph_norm": null,
          "morph_raw": null,
          "italics": false,
          "html_start": 28544,
          "html_end": 28586,
          "vhtml_start": 291,
          "vhtml_end": 333,
          "morph_gloss": null,
          "morph_features": null,
          "lemma": null,
          "transliteration": null,
          "pronunciation": null,
          "pos": null,
          "definition": null,
          "kjv_translation_count": null,
          "kjv_counts": null,
          "etymology": null,
          "outline": null,
          "text_start": 22,
          "text_end": 36,
          "token_id": "Ps.36.5#t0002"
        },
        {
          "text": "and",
          "strong_norm": null,
          "strong_raw": null,
          "morph_norm": null,
          "morph_raw": null,
          "italics": true,
          "html_start": 27337,
          "html_end": 27349,
          "vhtml_start": 341,
          "vhtml_end": 353,
          "morph_gloss": null,
          "morph_features": null,
          "lemma": null,
          "transliteration": null,
          "pronunciation": null,
          "pos": null,
          "definition": null,
          "kjv_translation_count": null,
          "kjv_counts": null,
          "etymology": null,
          "outline": null,
          "text_start": 38,
          "text_end": 41,
          "token_id": "Ps.36.5#t0006"
        },
        {
          "text": "thy faithfulness",
          "strong_norm": "H0530",
          "strong_raw": "H0530",
          "morph_norm": null,
          "morph_raw": null,
          "italics": false,
          "html_start": 28614,
          "html_end": 28658,
          "vhtml_start": 361,
          "vhtml_end": 405,
          "morph_gloss": null,
          "morph_features": null,
          "lemma": null,
          "transliteration": null,
          "pronunciation": null,
          "pos": null,
          "definition": null,
          "kjv_translation_count": null,
          "kjv_counts": null,
          "etymology": null,
          "outline": null,
          "text_start": 42,
          "text_end": 58,
          "token_id": "Ps.36.5#t0003"
        },
        {
          "text": "reacheth",
          "strong_norm": null,
          "strong_raw": null,
          "morph_norm": null,
          "morph_raw": null,
          "italics": true,
          "html_start": 28665,
          "html_end": 28682,
          "vhtml_start": 412,
          "vhtml_end": 429,
          "morph_gloss": null,
          "morph_features": null,
          "lemma": null,
          "transliteration": null,
          "pronunciation": null,
          "pos": null,
          "definition": null,
          "kjv_translation_count": null,
          "kjv_counts": null,
          "etymology": null,
          "outline": null,
          "text_start": 59,
          "text_end": 67,
          "token_id": "Ps.36.5#t0007"
        },
        {
          "text": "unto the clouds",
          "strong_norm": "H7834",
          "strong_raw": "H7834",
          "morph_norm": null,
          "morph_raw": null,
          "italics": false,
          "html_start": 28690,
          "html_end": 28733,
          "vhtml_start": 437,
          "vhtml_end": 480,
          "morph_gloss": null,
          "morph_features": null,
          "lemma": null,
          "transliteration": null,
          "pronunciation": null,
          "pos": null,
          "definition": null,
          "kjv_translation_count": null,
          "kjv_counts": null,
          "etymology": null,
          "outline": null,
          "text_start": 68,
          "text_end": 83,
          "token_id": "Ps.36.5#t0004"
        }
      ],
      "footnotes": []
    },
    {
      "ref": "Ps.36.6",
      "verse_num": 6,
      "text_plain": "Thy righteousness is like the great mountains; thy judgments are a great deep: O Lord, thou preservest man and beast.",
      "verse_html": "<span dir=\"ltr\" class=\"verse ltrDirection\"><a name=\"Ps.36.6\" class=\"verseLink\"><span class=\"verseNumber\">6</span></a><a name=\"Ps.36.6\" class=\"verseLink\"></a><span strong=\"H6666\">Thy righteousness</span> <span><em>is</em></span> <span strong=\"H0410G\">like the great</span> <span strong=\"H2042\">mountains</span>; <span strong=\"H4941G\">thy judgments</span> <span><em>are</em></span> <span strong=\"H7227A\">a great</span> <span strong=\"H8415\">deep</span>: <span strong=\"H3068G\">O <span class=\"small-caps\">Lord</span></span>, <span morph=\"strongMorph:TH8686\" strong=\"H3467\">thou preservest</span> <span strong=\"H0120G\">man</span> <span strong=\"H0929\">and beast</span>. <sup class=\"note\"><a ref=\"\" xref=\"\" notetype=\"study\">▼</a><span class=\"inlineNote\"><div><a class=\"sideNote\" name=\"note-N10130\"><strong>▼</strong></a><span class=\"bold\">&nbsp;the…</span>: Heb. the mountains of God</div></span></sup></span>",
      "tokens": [
        {
          "text": "Thy righteousness",
          "strong_norm": "H6666",
          "strong_raw": "H6666",
          "morph_norm": null,
          "morph_raw": null,
          "italics": false,
          "html_start": 28899,
          "html_end": 28944,
          "vhtml_start": 157,
          "vhtml_end": 202,
          "morph_gloss": null,
          "morph_features": null,
          "lemma": null,
          "transliteration": null,
          "pronunciation": null,
          "pos": null,
          "definition": null,
          "kjv_translation_count": null,
          "kjv_counts": null,
          "etymology": null,
          "outline": null,
          "text_start": 0,
          "text_end": 17,
          "token_id": "Ps.36.6#t0000"
        },
        {
          "text": "is",
          "strong_norm": null,
          "strong_raw": null,
          "morph_norm": null,
          "morph_raw": null,
          "italics": true,
          "html_start": 29849,
          "html_end": 29860,
          "vhtml_start": 209,
          "vhtml_end": 220,
          "morph_gloss": null,
          "morph_features": null,
          "lemma": null,
          "transliteration": null,
          "pronunciation": null,
          "pos": null,
          "definition": null,
          "kjv_translation_count": null,
          "kjv_counts": null,
          "etymology": null,
          "outline": null,
          "text_start": 18,
          "text_end": 20,
          "token_id": "Ps.36.6#t0010"
        },
        {
          "text": "like the great",
          "strong_norm": "H0410",
          "strong_raw": "H0410G",
          "morph_norm": null,
          "morph_raw": null,
          "italics": false,
          "html_start": 28970,
          "html_end": 29013,
          "vhtml_start": 228,
          "vhtml_end": 271,
          "morph_gloss": null,
          "morph_features": null,
          "lemma": null,
          "transliteration": null,
          "pronunciation": null,
          "pos": null,
          "definition": null,
          "kjv_translation_count": null,
          "kjv_counts": null,
          "etymology": null,
          "outline": null,
          "text_start": 21,
          "text_end": 35,
          "token_id": "Ps.36.6#t0001"
        },
        {
          "text": "mountains",
          "strong_norm": "H2042",
          "strong_raw": "H2042",
          "morph_norm": null,
          "morph_raw": null,
          "italics": false,
          "html_start": 29014,
          "html_end": 29051,
          "vhtml_start": 272,
          "vhtml_end": 309,
          "morph_gloss": null,
          "morph_features": null,
          "lemma": null,
          "transliteration": null,
          "pronunciation": null,
          "pos": null,
          "definition": null,
          "kjv_translation_count": null,
          "kjv_counts": null,
          "etymology": null,
          "outline": null,
          "text_start": 36,
          "text_end": 45,
          "token_id": "Ps.36.6#t0002"
        },
        {
          "text": "thy judgments",
          "strong_norm": "H4941",
          "strong_raw": "H4941G",
          "morph_norm": null,
          "morph_raw": null,
          "italics": false,
          "html_start": 29053,
          "html_end": 29095,
          "vhtml_start": 311,
          "vhtml_end": 353,
          "morph_gloss": null,
          "morph_features": null,
          "lemma": null,
          "transliteration": null,
          "pronunciation": null,
          "pos": null,
          "definition": null,
          "kjv_translation_count": null,
          "kjv_counts": null,
          "etymology": null,
          "outline": null,
          "text_start": 47,
          "text_end": 60,
          "token_id": "Ps.36.6#t0003"
        },
        {
          "text": "are",
          "strong_norm": null,
          "strong_raw": null,
          "morph_norm": null,
          "morph_raw": null,
          "italics": true,
          "html_start": 27093,
          "html_end": 27105,
          "vhtml_start": 360,
          "vhtml_end": 372,
          "morph_gloss": null,
          "morph_features": null,
          "lemma": null,
          "transliteration": null,
          "pronunciation": null,
          "pos": null,
          "definition": null,
          "kjv_translation_count": null,
          "kjv_counts": null,
          "etymology": null,
          "outline": null,
          "text_start": 61,
          "text_end": 64,
          "token_id": "Ps.36.6#t0011"
        },
        {
          "text": "a great",
          "strong_norm": "H7227",
          "strong_raw": "H7227A",
          "morph_norm": null,
          "morph_raw": null,
          "italics": false,
          "html_start": 29122,
          "html_end": 29158,
          "vhtml_start": 380,
          "vhtml_end": 416,
          "morph_gloss": null,
          "morph_features": null,
          "lemma": null,
          "transliteration": null,
          "pronunciation": null,
          "pos": null,
          "definition": null,
          "kjv_translation_count": null,
          "kjv_counts": null,
          "etymology": null,
          "outline": null,
          "text_start": 65,
          "text_end": 72,
          "token_id": "Ps.36.6#t0004"
        },
        {
          "text": "deep",
          "strong_norm": "H8415",
          "strong_raw": "H8415",
          "morph_norm": null,
          "morph_raw": null,
          "italics": false,
          "html_start": 29159,
          "html_end": 29191,
          "vhtml_start": 417,
          "vhtml_end": 449,
          "morph_gloss": null,
          "morph_features": null,
          "lemma": null,
          "transliteration": null,
          "pronunciation": null,
          "pos": null,
          "definition": null,
          "kjv_translation_count": null,
          "kjv_counts": null,
          "etymology": null,
          "outline": null,
          "text_start": 73,
          "text_end": 77,
          "token_id": "Ps.36.6#t0005"
        },
        {
          "text": "O Lord",
          "strong_norm": "H3068",
          "strong_raw": "H3068G",
          "morph_norm": null,
          "morph_raw": null,
          "italics": false,
          "html_start": 29193,
          "html_end": 29260,
          "vhtml_start": 451,
          "vhtml_end": 518,
          "morph_gloss": null,
          "morph_features": null,
          "lemma": null,
          "transliteration": null,
          "pronunciation": null,
          "pos": null,
          "definition": null,
          "kjv_translation_count": null,
          "kjv_counts": null,
          "etymology": null,
          "outline": null,
          "text_start": 79,
          "text_end": 85,
          "token_id": "Ps.36.6#t0006"
        },
        {
          "text": "thou preservest",
          "strong_norm": "H3467",
          "strong_raw": "H3467",
          "morph_norm": "TH8686",
          "morph_raw": "strongMorph:TH8686",
          "italics": false,
          "html_start": 29262,
          "html_end": 29332,
          "vhtml_start": 520,
          "vhtml_end": 590,
          "morph_gloss": null,
          "morph_features": null,
          "lemma": null,
          "transliteration": null,
          "pronunciation": null,
          "pos": null,
          "definition": null,
          "kjv_translation_count": null,
          "kjv_counts": null,
          "etymology": null,
          "outline": null,
          "text_start": 87,
          "text_end": 102,
          "token_id": "Ps.36.6#t0007"
        },
        {
          "text": "man",
          "strong_norm": "H0120",
          "strong_raw": "H0120G",
          "morph_norm": null,
          "morph_raw": null,
          "italics": false,
          "html_start": 29333,
          "html_end": 29365,
          "vhtml_start": 591,
          "vhtml_end": 623,
          "morph_gloss": null,
          "morph_features": null,
          "lemma": null,
          "transliteration": null,
          "pronunciation": null,
          "pos": null,
          "definition": null,
          "kjv_translation_count": null,
          "kjv_counts": null,
          "etymology": null,
          "outline": null,
          "text_start": 103,
          "text_end": 106,
          "token_id": "Ps.36.6#t0008"
        },
        {
          "text": "and beast",
          "strong_norm": "H0929",
          "strong_raw": "H0929",
          "morph_norm": null,
          "morph_raw": null,
          "italics": false,
          "html_start": 29366,
          "html_end": 29403,
          "vhtml_start": 624,
          "vhtml_end": 661,
          "morph_gloss": null,
          "morph_features": null,
          "lemma": null,
          "transliteration": null,
          "pronunciation": null,
          "pos": null,
          "definition": null,
          "kjv_translation_count": null,
          "kjv_counts": null,
          "etymology": null,
          "outline": null,
          "text_start": 107,
          "text_end": 116,
          "token_id": "Ps.36.6#t0009"
        }
      ],
      "footnotes": [
        {
          "marker": "▼",
          "notetype": "study",
          "ref_attr": null,
          "xref_attr": null,
          "body_text": "▼ the…: Heb. the mountains of God",
          "body_html": "<span class=\"inlineNote\"><div><a class=\"sideNote\" name=\"note-N10130\"><strong>▼</strong></a><span class=\"bold\">&nbsp;the…</span>: Heb. the mountains of God</div></span>"
        }
      ]
    },
    {
      "ref": "Ps.36.7",
      "verse_num": 7,
      "text_plain": "How excellent is thy lovingkindness, O God! therefore the children of men put their trust under the shadow of thy wings.",
      "verse_html": "<span dir=\"ltr\" class=\"verse ltrDirection\"><a name=\"Ps.36.7\" class=\"verseLink\"><span class=\"verseNumber\">7</span></a><a name=\"Ps.36.7\" class=\"verseLink\"></a><span strong=\"H3368\">How excellent</span> <span><em>is</em></span> <span strong=\"H2617A\">thy lovingkindness</span>, <span strong=\"H0430G\">O God</span>! <span strong=\"H1121A\">therefore the children</span> <span strong=\"H0120G\">of men</span> <span morph=\"strongMorph:TH8799\" strong=\"H2620\">put their trust</span> <span strong=\"H6738\">under the shadow</span> <span strong=\"H3671\">of thy wings</span>. <sup class=\"note\"><a ref=\"\" xref=\"\" notetype=\"study\">▼</a><span class=\"inlineNote\"><div><a class=\"sideNote\" name=\"note-N1015F\"><strong>▼</strong></a><span class=\"bold\">&nbsp;excellent</span>: Heb. precious</div></span></sup></span>",
      "tokens": [
        {
          "text": "How excellent",
          "strong_norm": "H3368",
          "strong_raw": "H3368",
          "morph_norm": null,
          "morph_raw": null,
          "italics": false,
          "html_start": 29801,
          "html_end": 29842,
          "vhtml_start": 157,
          "vhtml_end": 198,
          "morph_gloss": null,
          "morph_features": null,
          "lemma": null,
          "transliteration": null,
          "pronunciation": null,
          "pos": null,
          "definition": null,
          "kjv_translation_count": null,
          "kjv_counts": null,
          "etymology": null,
          "outline": null,
          "text_start": 0,
          "text_end": 13,
          "token_id": "Ps.36.7#t0000"
        },
        {
          "text": "is",
          "strong_norm": null,
          "strong_raw": null,
          "morph_norm": null,
          "morph_raw": null,
          "italics": true,
          "html_start": 31352,
          "html_end": 31363,
          "vhtml_start": 205,
          "vhtml_end": 216,
          "morph_gloss": null,
          "morph_features": null,
          "lemma": null,
          "transliteration": null,
          "pronunciation": null,
          "pos": null,
          "definition": null,
          "kjv_translation_count": null,
          "kjv_counts": null,
          "etymology": null,
          "outline": null,
          "text_start": 14,
          "text_end": 16,
          "token_id": "Ps.36.7#t0008"
        },
        {
          "text": "thy lovingkindness",
          "strong_norm": "H2617",
          "strong_raw": "H2617A",
          "morph_norm": null,
          "morph_raw": null,
          "italics": false,
          "html_start": 29868,
          "html_end": 29915,
          "vhtml_start": 224,
          "vhtml_end": 271,
          "morph_gloss": null,
          "morph_features": null,
          "lemma": null,
          "transliteration": null,
          "pronunciation": null,
          "pos": null,
          "definition": null,
          "kjv_translation_count": null,
          "kjv_counts": null,
          "etymology": null,
          "outline": null,
          "text_start": 17,
          "text_end": 35,
          "token_id": "Ps.36.7#t0001"
        },
        {
          "text": "O God",
          "strong_norm": "H0430",
          "strong_raw": "H0430G",
          "morph_norm": null,
          "morph_raw": null,
          "italics": false,
          "html_start": 29917,
          "html_end": 29951,
          "vhtml_start": 273,
          "vhtml_end": 307,
          "morph_gloss": null,
          "morph_features": null,
          "lemma": null,
          "transliteration": null,
          "pronunciation": null,
          "pos": null,
          "definition": null,
          "kjv_translation_count": null,
          "kjv_counts": null,
          "etymology": null,
          "outline": null,
          "text_start": 37,
          "text_end": 42,
          "token_id": "Ps.36.7#t0002"
        },
        {
          "text": "therefore the children",
          "strong_norm": "H1121",
          "strong_raw": "H1121A",
          "morph_norm": null,
          "morph_raw": null,
          "italics": false,
          "html_start": 29953,
          "html_end": 30004,
          "vhtml_start": 309,
          "vhtml_end": 360,
          "morph_gloss": null,
          "morph_features": null,
          "lemma": null,
          "transliteration": null,
          "pronunciation": null,
          "pos": null,
          "definition": null,
          "kjv_translation_count": null,
          "kjv_counts": null,
          "etymology": null,
          "outline": null,
          "text_start": 44,
          "text_end": 66,
          "token_id": "Ps.36.7#t0003"
        },
        {
          "text": "of men",
          "strong_norm": "H0120",
          "strong_raw": "H0120G",
          "morph_norm": null,
          "morph_raw": null,
          "italics": false,
          "html_start": 30005,
          "html_end": 30040,
          "vhtml_start": 361,
          "vhtml_end": 396,
          "morph_gloss": null,
          "morph_features": null,
          "lemma": null,
          "transliteration": null,
          "pronunciation": null,
          "pos": null,
          "definition": null,
          "kjv_translation_count": null,
          "kjv_counts": null,
          "etymology": null,
          "outline": null,
          "text_start": 67,
          "text_end": 73,
          "token_id": "Ps.36.7#t0004"
        },
        {
          "text": "put their trust",
          "strong_norm": "H2620",
          "strong_raw": "H2620",
          "morph_norm": "TH8799",
          "morph_raw": "strongMorph:TH8799",
          "italics": false,
          "html_start": 30041,
          "html_end": 30111,
          "vhtml_start": 397,
          "vhtml_end": 467,
          "morph_gloss": null,
          "morph_features": null,
          "lemma": null,
          "transliteration": null,
          "pronunciation": null,
          "pos": null,
          "definition": null,
          "kjv_translation_count": null,
          "kjv_counts": null,
          "etymology": null,
          "outline": null,
          "text_start": 74,
          "text_end": 89,
          "token_id": "Ps.36.7#t0005"
        },
        {
          "text": "under the shadow",
          "strong_norm": "H6738",
          "strong_raw": "H6738",
          "morph_norm": null,
          "morph_raw": null,
          "italics": false,
          "html_start": 30112,
          "html_end": 30156,
          "vhtml_start": 468,
          "vhtml_end": 512,
          "morph_gloss": null,
          "morph_features": null,
          "lemma": null,
          "transliteration": null,
          "pronunciation": null,
          "pos": null,
          "definition": null,
          "kjv_translation_count": null,
          "kjv_counts": null,
          "etymology": null,
          "outline": null,
          "text_start": 90,
          "text_end": 106,
          "token_id": "Ps.36.7#t0006"
        },
        {
          "text": "of thy wings",
          "strong_norm": "H3671",
          "strong_raw": "H3671",
          "morph_norm": null,
          "morph_raw": null,
          "italics": false,
          "html_start": 30157,
          "html_end": 30197,
          "vhtml_start": 513,
          "vhtml_end": 553,
          "morph_gloss": null,
          "morph_features": null,
          "lemma": null,
          "transliteration": null,
          "pronunciation": null,
          "pos": null,
          "definition": null,
          "kjv_translation_count": null,
          "kjv_counts": null,
          "etymology": null,
          "outline": null,
          "text_start": 107,
          "text_end": 119,
          "token_id": "Ps.36.7#t0007"
        }
      ],
      "footnotes": [
        {
          "marker": "▼",
          "notetype": "study",
          "ref_attr": null,
          "xref_attr": null,
          "body_text": "▼ excellent: Heb. precious",
          "body_html": "<span class=\"inlineNote\"><div><a class=\"sideNote\" name=\"note-N1015F\"><strong>▼</strong></a><span class=\"bold\">&nbsp;excellent</span>: Heb. precious</div></span>"
        }
      ]
    },
    {
      "ref": "Ps.36.8",
      "verse_num": 8,
      "text_plain": "They shall be abundantly satisfied with the fatness of thy house; and thou shalt make them drink of the river of thy pleasures.",
      "verse_html": "<span dir=\"ltr\" class=\"verse ltrDirection\"><a name=\"Ps.36.8\" class=\"verseLink\"><span class=\"verseNumber\">8</span></a><a name=\"Ps.36.8\" class=\"verseLink\"></a><span morph=\"strongMorph:TH8799\" strong=\"H7301\">They shall be abundantly satisfied</span> <span strong=\"H1880\">with the fatness</span> <span strong=\"H1004B\">of thy house</span>; <span morph=\"strongMorph:TH8686\" strong=\"H8248H\">and thou shalt make them drink</span> <span strong=\"H5158A\">of the river</span> <span strong=\"H5730A\">of thy pleasures</span>. <sup class=\"note\"><a ref=\"\" xref=\"\" notetype=\"study\">▼</a><span class=\"inlineNote\"><div><a class=\"sideNote\" name=\"note-N10183\"><strong>▼</strong></a><span class=\"bold\">&nbsp;abundantly…</span>: Heb. watered</div></span></sup></span>",
      "tokens": [
        {
          "text": "They shall be abundantly satisfied",
          "strong_norm": "H7301",
          "strong_raw": "H7301",
          "morph_norm": "TH8799",
          "morph_raw": "strongMorph:TH8799",
          "italics": false,
          "html_start": 30588,
          "html_end": 30677,
          "vhtml_start": 157,
          "vhtml_end": 246,
          "morph_gloss": null,
          "morph_features": null,
          "lemma": null,
          "transliteration": null,
          "pronunciation": null,
          "pos": null,
          "definition": null,
          "kjv_translation_count": null,
          "kjv_counts": null,
          "etymology": null,
          "outline": null,
          "text_start": 0,
          "text_end": 34,
          "token_id": "Ps.36.8#t0000"
        },
        {
          "text": "with the fatness",
          "strong_norm": "H1880",
          "strong_raw": "H1880",
          "morph_norm": null,
          "morph_raw": null,
          "italics": false,
          "html_start": 30678,
          "html_end": 30722,
          "vhtml_start": 247,
          "vhtml_end": 291,
          "morph_gloss": null,
          "morph_features": null,
          "lemma": null,
          "transliteration": null,
          "pronunciation": null,
          "pos": null,
          "definition": null,
          "kjv_translation_count": null,
          "kjv_counts": null,
          "etymology": null,
          "outline": null,
          "text_start": 35,
          "text_end": 51,
          "token_id": "Ps.36.8#t0001"
        },
        {
          "text": "of thy house",
          "strong_norm": "H1004",
          "strong_raw": "H1004B",
          "morph_norm": null,
          "morph_raw": null,
          "italics": false,
          "html_start": 30723,
          "html_end": 30764,
          "vhtml_start": 292,
          "vhtml_end": 333,
          "morph_gloss": null,
          "morph_features": null,
          "lemma": null,
          "transliteration": null,
          "pronunciation": null,
          "pos": null,
          "definition": null,
          "kjv_translation_count": null,
          "kjv_counts": null,
          "etymology": null,
          "outline": null,
          "text_start": 52,
          "text_end": 64,
          "token_id": "Ps.36.8#t0002"
        },
        {
          "text": "and thou shalt make them drink",
          "strong_norm": "H8248",
          "strong_raw": "H8248H",
          "morph_norm": "TH8686",
          "morph_raw": "strongMorph:TH8686",
          "italics": false,
          "html_start": 30766,
          "html_end": 30852,
          "vhtml_start": 335,
          "vhtml_end": 421,
          "morph_gloss": null,
          "morph_features": null,
          "lemma": null,
          "transliteration": null,
          "pronunciation": null,
          "pos": null,
          "definition": null,
          "kjv_translation_count": null,
          "kjv_counts": null,
          "etymology": null,
          "outline": null,
          "text_start": 66,
          "text_end": 96,
          "token_id": "Ps.36.8#t0003"
        },
        {
          "text": "of the river",
          "strong_norm": "H5158",
          "strong_raw": "H5158A",
          "morph_norm": null,
          "morph_raw": null,
          "italics": false,
          "html_start": 30853,
          "html_end": 30894,
          "vhtml_start": 422,
          "vhtml_end": 463,
          "morph_gloss": null,
          "morph_features": null,
          "lemma": null,
          "transliteration": null,
          "pronunciation": null,
          "pos": null,
          "definition": null,
          "kjv_translation_count": null,
          "kjv_counts": null,
          "etymology": null,
          "outline": null,
          "text_start": 97,
          "text_end": 109,
          "token_id": "Ps.36.8#t0004"
        },
        {
          "text": "of thy pleasures",
          "strong_norm": "H5730",
          "strong_raw": "H5730A",
          "morph_norm": null,
          "morph_raw": null,
          "italics": false,
          "html_start": 30895,
          "html_end": 30940,
          "vhtml_start": 464,
          "vhtml_end": 509,
          "morph_gloss": null,
          "morph_features": null,
          "lemma": null,
          "transliteration": null,
          "pronunciation": null,
          "pos": null,
          "definition": null,
          "kjv_translation_count": null,
          "kjv_counts": null,
          "etymology": null,
          "outline": null,
          "text_start": 110,
          "text_end": 126,
          "token_id": "Ps.36.8#t0005"
        }
      ],
      "footnotes": [
        {
          "marker": "▼",
          "notetype": "study",
          "ref_attr": null,
          "xref_attr": null,
          "body_text": "▼ abundantly…: Heb. watered",
          "body_html": "<span class=\"inlineNote\"><div><a class=\"sideNote\" name=\"note-N10183\"><strong>▼</strong></a><span class=\"bold\">&nbsp;abundantly…</span>: Heb. watered</div></span>"
        }
      ]
    },
    {
      "ref": "Ps.36.9",
      "verse_num": 9,
      "text_plain": "For with thee is the fountain of life: in thy light shall we see light.",
      "verse_html": "<span dir=\"ltr\" class=\"verse ltrDirection\"><a name=\"Ps.36.9\" class=\"verseLink\"><span class=\"verseNumber\">9</span></a><a name=\"Ps.36.9\" class=\"verseLink\"></a>For with thee <span><em>is</em></span> <span strong=\"H4726\">the fountain</span> <span strong=\"H2416E\">of life</span>: <span strong=\"H0216\">in thy light</span> <span morph=\"strongMorph:TH8799\" strong=\"H7200G\">shall we see</span> <span strong=\"H0216\">light</span>.</span>",
      "tokens": [
        {
          "text": "is",
          "strong_norm": null,
          "strong_raw": null,
          "morph_norm": null,
          "morph_raw": null,
          "italics": true,
          "html_start": 28525,
          "html_end": 28536,
          "vhtml_start": 177,
          "vhtml_end": 188,
          "morph_gloss": null,
          "morph_features": null,
          "lemma": null,
          "transliteration": null,
          "pronunciation": null,
          "pos": null,
          "definition": null,
          "kjv_translation_count": null,
          "kjv_counts": null,
          "etymology": null,
          "outline": null,
          "text_start": 14,
          "text_end": 16,
          "token_id": "Ps.36.9#t0005"
        },
        {
          "text": "the fountain",
          "strong_norm": "H4726",
          "strong_raw": "H4726",
          "morph_norm": null,
          "morph_raw": null,
          "italics": false,
          "html_start": 31371,
          "html_end": 31411,
          "vhtml_start": 196,
          "vhtml_end": 236,
          "morph_gloss": null,
          "morph_features": null,
          "lemma": null,
          "transliteration": null,
          "pronunciation": null,
          "pos": null,
          "definition": null,
          "kjv_translation_count": null,
          "kjv_counts": null,
          "etymology": null,
          "outline": null,
          "text_start": 17,
          "text_end": 29,
          "token_id": "Ps.36.9#t0000"
        },
        {
          "text": "of life",
          "strong_norm": "H2416",
          "strong_raw": "H2416E",
          "morph_norm": null,
          "morph_raw": null,
          "italics": false,
          "html_start": 31412,
          "html_end": 31448,
          "vhtml_start": 237,
          "vhtml_end": 273,
          "morph_gloss": null,
          "morph_features": null,
          "lemma": null,
          "transliteration": null,
          "pronunciation": null,
          "pos": null,
          "definition": null,
          "kjv_translation_count": null,
          "kjv_counts": null,
          "etymology": null,
          "outline": null,
          "text_start": 30,
          "text_end": 37,
          "token_id": "Ps.36.9#t0001"
        },
        {
          "text": "in thy light",
          "strong_norm": "H0216",
          "strong_raw": "H0216",
          "morph_norm": null,
          "morph_raw": null,
          "italics": false,
          "html_start": 31450,
          "html_end": 31490,
          "vhtml_start": 275,
          "vhtml_end": 315,
          "morph_gloss": null,
          "morph_features": null,
          "lemma": null,
          "transliteration": null,
          "pronunciation": null,
          "pos": null,
          "definition": null,
          "kjv_translation_count": null,
          "kjv_counts": null,
          "etymology": null,
          "outline": null,
          "text_start": 39,
          "text_end": 51,
          "token_id": "Ps.36.9#t0002"
        },
        {
          "text": "shall we see",
          "strong_norm": "H7200",
          "strong_raw": "H7200G",
          "morph_norm": "TH8799",
          "morph_raw": "strongMorph:TH8799",
          "italics": false,
          "html_start": 31491,
          "html_end": 31559,
          "vhtml_start": 316,
          "vhtml_end": 384,
          "morph_gloss": null,
          "morph_features": null,
          "lemma": null,
          "transliteration": null,
          "pronunciation": null,
          "pos": null,
          "definition": null,
          "kjv_translation_count": null,
          "kjv_counts": null,
          "etymology": null,
          "outline": null,
          "text_start": 52,
          "text_end": 64,
          "token_id": "Ps.36.9#t0003"
        },
        {
          "text": "light",
          "strong_norm": "H0216",
          "strong_raw": "H0216",
          "morph_norm": null,
          "morph_raw": null,
          "italics": false,
          "html_start": 31560,
          "html_end": 31593,
          "vhtml_start": 385,
          "vhtml_end": 418,
          "morph_gloss": null,
          "morph_features": null,
          "lemma": null,
          "transliteration": null,
          "pronunciation": null,
          "pos": null,
          "definition": null,
          "kjv_translation_count": null,
          "kjv_counts": null,
          "etymology": null,
          "outline": null,
          "text_start": 65,
          "text_end": 70,
          "token_id": "Ps.36.9#t0004"
        }
      ],
      "footnotes": []
    },
    {
      "ref": "Ps.36.10",
      "verse_num": 10,
      "text_plain": "O continue thy lovingkindness unto them that know thee; and thy righteousness to the upright in heart.",
      "verse_html": "<span dir=\"ltr\" class=\"verse ltrDirection\"><a name=\"Ps.36.10\" class=\"verseLink\"><span class=\"verseNumber\">10</span></a><a name=\"Ps.36.10\" class=\"verseLink\"></a><span morph=\"strongMorph:TH8798\" strong=\"H4900\">O continue</span> <span strong=\"H2617A\">thy lovingkindness</span> <span morph=\"strongMorph:TH8802\" strong=\"H3045\">unto them that know</span> <span strong=\"H6666\">thee; and thy righteousness</span> <span strong=\"H3477G\">to the upright</span> <span strong=\"H3820A\">in heart</span>. <sup class=\"note\"><a ref=\"\" xref=\"\" notetype=\"study\">▼</a><span class=\"inlineNote\"><div><a class=\"sideNote\" name=\"note-N101C3\"><strong>▼</strong></a><span class=\"bold\">&nbsp;continue</span>: Heb. draw out at length</div></span></sup></span>",
      "tokens": [
        {
          "text": "O continue",
          "strong_norm": "H4900",
          "strong_raw": "H4900",
          "morph_norm": "TH8798",
          "morph_raw": "strongMorph:TH8798",
          "italics": false,
          "html_start": 31762,
          "html_end": 31827,
          "vhtml_start": 160,
          "vhtml_end": 225,
          "morph_gloss": null,
          "morph_features": null,
          "lemma": null,
          "transliteration": null,
          "pronunciation": null,
          "pos": null,
          "definition": null,
          "kjv_translation_count": null,
          "kjv_counts": null,
          "etymology": null,
          "outline": null,
          "text_start": 0,
          "text_end": 10,
          "token_id": "Ps.36.10#t0000"
        },
        {
          "text": "thy lovingkindness",
          "strong_norm": "H2617",
          "strong_raw": "H2617A",
          "morph_norm": null,
          "morph_raw": null,
          "italics": false,
          "html_start": 31828,
          "html_end": 31875,
          "vhtml_start": 226,
          "vhtml_end": 273,
          "morph_gloss": null,
          "morph_features": null,
          "lemma": null,
          "transliteration": null,
          "pronunciation": null,
          "pos": null,
          "definition": null,
          "kjv_translation_count": null,
          "kjv_counts": null,
          "etymology": null,
          "outline": null,
          "text_start": 11,
          "text_end": 29,
          "token_id": "Ps.36.10#t0001"
        },
        {
          "text": "unto them that know",
          "strong_norm": "H3045",
          "strong_raw": "H3045",
          "morph_norm": "TH8802",
          "morph_raw": "strongMorph:TH8802",
          "italics": false,
          "html_start": 31876,
          "html_end": 31950,
          "vhtml_start": 274,
          "vhtml_end": 348,
          "morph_gloss": null,
          "morph_features": null,
          "lemma": null,
          "transliteration": null,
          "pronunciation": null,
          "pos": null,
          "definition": null,
          "kjv_translation_count": null,
          "kjv_counts": null,
          "etymology": null,
          "outline": null,
          "text_start": 30,
          "text_end": 49,
          "token_id": "Ps.36.10#t0002"
        },
        {
          "text": "thee; and thy righteousness",
          "strong_norm": "H6666",
          "strong_raw": "H6666",
          "morph_norm": null,
          "morph_raw": null,
          "italics": false,
          "html_start": 31951,
          "html_end": 32006,
          "vhtml_start": 349,
          "vhtml_end": 404,
          "morph_gloss": null,
          "morph_features": null,
          "lemma": null,
          "transliteration": null,
          "pronunciation": null,
          "pos": null,
          "definition": null,
          "kjv_translation_count": null,
          "kjv_counts": null,
          "etymology": null,
          "outline": null,
          "text_start": 50,
          "text_end": 77,
          "token_id": "Ps.36.10#t0003"
        },
        {
          "text": "to the upright",
          "strong_norm": "H3477",
          "strong_raw": "H3477G",
          "morph_norm": null,
          "morph_raw": null,
          "italics": false,
          "html_start": 32007,
          "html_end": 32050,
          "vhtml_start": 405,
          "vhtml_end": 448,
          "morph_gloss": null,
          "morph_features": null,
          "lemma": null,
          "transliteration": null,
          "pronunciation": null,
          "pos": null,
          "definition": null,
          "kjv_translation_count": null,
          "kjv_counts": null,
          "etymology": null,
          "outline": null,
          "text_start": 78,
          "text_end": 92,
          "token_id": "Ps.36.10#t0004"
        },
        {
          "text": "in heart",
          "strong_norm": "H3820",
          "strong_raw": "H3820A",
          "morph_norm": null,
          "morph_raw": null,
          "italics": false,
          "html_start": 32051,
          "html_end": 32088,
          "vhtml_start": 449,
          "vhtml_end": 486,
          "morph_gloss": null,
          "morph_features": null,
          "lemma": null,
          "transliteration": null,
          "pronunciation": null,
          "pos": null,
          "definition": null,
          "kjv_translation_count": null,
          "kjv_counts": null,
          "etymology": null,
          "outline": null,
          "text_start": 93,
          "text_end": 101,
          "token_id": "Ps.36.10#t0005"
        }
      ],
      "footnotes": [
        {
          "marker": "▼",
          "notetype": "study",
          "ref_attr": null,
          "xref_attr": null,
          "body_text": "▼ continue: Heb. draw out at length",
          "body_html": "<span class=\"inlineNote\"><div><a class=\"sideNote\" name=\"note-N101C3\"><strong>▼</strong></a><span class=\"bold\">&nbsp;continue</span>: Heb. draw out at length</div></span>"
        }
      ]
    },
    {
      "ref": "Ps.36.11",
      "verse_num": 11,
      "text_plain": "Let not the foot of pride come against me, and let not the hand of the wicked remove me.",
      "verse_html": "<span dir=\"ltr\" class=\"verse ltrDirection\"><a name=\"Ps.36.11\" class=\"verseLink\"><span class=\"verseNumber\">11</span></a><a name=\"Ps.36.11\" class=\"verseLink\"></a><span strong=\"H7272\">Let not the foot</span> <span strong=\"H1346\">of pride</span> <span morph=\"strongMorph:TH8799\" strong=\"H0935G\">come</span> <span strong=\"H3027H\">against me, and let not the hand</span> <span strong=\"H7563\">of the wicked</span> <span morph=\"strongMorph:TH8686\" strong=\"H5110\">remove</span> me.</span>",
      "tokens": [
        {
          "text": "Let not the foot",
          "strong_norm": "H7272",
          "strong_raw": "H7272",
          "morph_norm": null,
          "morph_raw": null,
          "italics": false,
          "html_start": 32491,
          "html_end": 32535,
          "vhtml_start": 160,
          "vhtml_end": 204,
          "morph_gloss": null,
          "morph_features": null,
          "lemma": null,
          "transliteration": null,
          "pronunciation": null,
          "pos": null,
          "definition": null,
          "kjv_translation_count": null,
          "kjv_counts": null,
          "etymology": null,
          "outline": null,
          "text_start": 0,
          "text_end": 16,
          "token_id": "Ps.36.11#t0000"
        },
        {
          "text": "of pride",
          "strong_norm": "H1346",
          "strong_raw": "H1346",
          "morph_norm": null,
          "morph_raw": null,
          "italics": false,
          "html_start": 32536,
          "html_end": 32572,
          "vhtml_start": 205,
          "vhtml_end": 241,
          "morph_gloss": null,
          "morph_features": null,
          "lemma": null,
          "transliteration": null,
          "pronunciation": null,
          "pos": null,
          "definition": null,
          "kjv_translation_count": null,
          "kjv_counts": null,
          "etymology": null,
          "outline": null,
          "text_start": 17,
          "text_end": 25,
          "token_id": "Ps.36.11#t0001"
        },
        {
          "text": "come",
          "strong_norm": "H0935",
          "strong_raw": "H0935G",
          "morph_norm": "TH8799",
          "morph_raw": "strongMorph:TH8799",
          "italics": false,
          "html_start": 32573,
          "html_end": 32633,
          "vhtml_start": 242,
          "vhtml_end": 302,
          "morph_gloss": null,
          "morph_features": null,
          "lemma": null,
          "transliteration": null,
          "pronunciation": null,
          "pos": null,
          "definition": null,
          "kjv_translation_count": null,
          "kjv_counts": null,
          "etymology": null,
          "outline": null,
          "text_start": 26,
          "text_end": 30,
          "token_id": "Ps.36.11#t0002"
        },
        {
          "text": "against me, and let not the hand",
          "strong_norm": "H3027",
          "strong_raw": "H3027H",
          "morph_norm": null,
          "morph_raw": null,
          "italics": false,
          "html_start": 32634,
          "html_end": 32695,
          "vhtml_start": 303,
          "vhtml_end": 364,
          "morph_gloss": null,
          "morph_features": null,
          "lemma": null,
          "transliteration": null,
          "pronunciation": null,
          "pos": null,
          "definition": null,
          "kjv_translation_count": null,
          "kjv_counts": null,
          "etymology": null,
          "outline": null,
          "text_start": 31,
          "text_end": 63,
          "token_id": "Ps.36.11#t0003"
        },
        {
          "text": "of the wicked",
          "strong_norm": "H7563",
          "strong_raw": "H7563",
          "morph_norm": null,
          "morph_raw": null,
          "italics": false,
          "html_start": 32696,
          "html_end": 32737,
          "vhtml_start": 365,
          "vhtml_end": 406,
          "morph_gloss": null,
          "morph_features": null,
          "lemma": null,
          "transliteration": null,
          "pronunciation": null,
          "pos": null,
          "definition": null,
          "kjv_translation_count": null,
          "kjv_counts": null,
          "etymology": null,
          "outline": null,
          "text_start": 64,
          "text_end": 77,
          "token_id": "Ps.36.11#t0004"
        },
        {
          "text": "remove",
          "strong_norm": "H5110",
          "strong_raw": "H5110",
          "morph_norm": "TH8686",
          "morph_raw": "strongMorph:TH8686",
          "italics": false,
          "html_start": 32738,
          "html_end": 32799,
          "vhtml_start": 407,
          "vhtml_end": 468,
          "morph_gloss": null,
          "morph_features": null,
          "lemma": null,
          "transliteration": null,
          "pronunciation": null,
          "pos": null,
          "definition": null,
          "kjv_translation_count": null,
          "kjv_counts": null,
          "etymology": null,
          "outline": null,
          "text_start": 78,
          "text_end": 84,
          "token_id": "Ps.36.11#t0005"
        }
      ],
      "footnotes": []
    },
    {
      "ref": "Ps.36.12",
      "verse_num": 12,
      "text_plain": "There are the workers of iniquity fallen: they are cast down, and shall not be able to rise.",
      "verse_html": "<span dir=\"ltr\" class=\"verse ltrDirection\"><a name=\"Ps.36.12\" class=\"verseLink\"><span class=\"verseNumber\">12</span></a><a name=\"Ps.36.12\" class=\"verseLink\"></a><span morph=\"strongMorph:TH8802\" strong=\"H6466\">There are the workers</span> <span strong=\"H0205G\">of iniquity</span> <span morph=\"strongMorph:TH8804\" strong=\"H5307G\">fallen</span>: <span morph=\"strongMorph:TH8795\" strong=\"H1760A\">they are cast down</span>, <span morph=\"strongMorph:TH8804\" strong=\"H3201\">and shall not be able</span> <span morph=\"strongMorph:TH8800\" strong=\"H6965B\">to rise</span>. </span>",
      "tokens": [
        {
          "text": "There are the workers",
          "strong_norm": "H6466",
          "strong_raw": "H6466",
          "morph_norm": "TH8802",
          "morph_raw": "strongMorph:TH8802",
          "italics": false,
          "html_start": 32971,
          "html_end": 33047,
          "vhtml_start": 160,
          "vhtml_end": 236,
          "morph_gloss": null,
          "morph_features": null,
          "lemma": null,
          "transliteration": null,
          "pronunciation": null,
          "pos": null,
          "definition": null,
          "kjv_translation_count": null,
          "kjv_counts": null,
          "etymology": null,
          "outline": null,
          "text_start": 0,
          "text_end": 21,
          "token_id": "Ps.36.12#t0000"
        },
        {
          "text": "of iniquity",
          "strong_norm": "H0205",
          "strong_raw": "H0205G",
          "morph_norm": null,
          "morph_raw": null,
          "italics": false,
          "html_start": 33048,
          "html_end": 33088,
          "vhtml_start": 237,
          "vhtml_end": 277,
          "morph_gloss": null,
          "morph_features": null,
          "lemma": null,
          "transliteration": null,
          "pronunciation": null,
          "pos": null,
          "definition": null,
          "kjv_translation_count": null,
          "kjv_counts": null,
          "etymology": null,
          "outline": null,
          "text_start": 22,
          "text_end": 33,
          "token_id": "Ps.36.12#t0001"
        },
        {
          "text": "fallen",
          "strong_norm": "H5307",
          "strong_raw": "H5307G",
          "morph_norm": "TH8804",
          "morph_raw": "strongMorph:TH8804",
          "italics": false,
          "html_start": 33089,
          "html_end": 33151,
          "vhtml_start": 278,
          "vhtml_end": 340,
          "morph_gloss": null,
          "morph_features": null,
          "lemma": null,
          "transliteration": null,
          "pronunciation": null,
          "pos": null,
          "definition": null,
          "kjv_translation_count": null,
          "kjv_counts": null,
          "etymology": null,
          "outline": null,
          "text_start": 34,
          "text_end": 40,
          "token_id": "Ps.36.12#t0002"
        },
        {
          "text": "they are cast down",
          "strong_norm": "H1760",
          "strong_raw": "H1760A",
          "morph_norm": "TH8795",
          "morph_raw": "strongMorph:TH8795",
          "italics": false,
          "html_start": 33153,
          "html_end": 33227,
          "vhtml_start": 342,
          "vhtml_end": 416,
          "morph_gloss": null,
          "morph_features": null,
          "lemma": null,
          "transliteration": null,
          "pronunciation": null,
          "pos": null,
          "definition": null,
          "kjv_translation_count": null,
          "kjv_counts": null,
          "etymology": null,
          "outline": null,
          "text_start": 42,
          "text_end": 60,
          "token_id": "Ps.36.12#t0003"
        },
        {
          "text": "and shall not be able",
          "strong_norm": "H3201",
          "strong_raw": "H3201",
          "morph_norm": "TH8804",
          "morph_raw": "strongMorph:TH8804",
          "italics": false,
          "html_start": 33229,
          "html_end": 33305,
          "vhtml_start": 418,
          "vhtml_end": 494,
          "morph_gloss": null,
          "morph_features": null,
          "lemma": null,
          "transliteration": null,
          "pronunciation": null,
          "pos": null,
          "definition": null,
          "kjv_translation_count": null,
          "kjv_counts": null,
          "etymology": null,
          "outline": null,
          "text_start": 62,
          "text_end": 83,
          "token_id": "Ps.36.12#t0004"
        },
        {
          "text": "to rise",
          "strong_norm": "H6965",
          "strong_raw": "H6965B",
          "morph_norm": "TH8800",
          "morph_raw": "strongMorph:TH8800",
          "italics": false,
          "html_start": 33306,
          "html_end": 33369,
          "vhtml_start": 495,
          "vhtml_end": 558,
          "morph_gloss": null,
          "morph_features": null,
          "lemma": null,
          "transliteration": null,
          "pronunciation": null,
          "pos": null,
          "definition": null,
          "kjv_translation_count": null,
          "kjv_counts": null,
          "etymology": null,
          "outline": null,
          "text_start": 84,
          "text_end": 91,
          "token_id": "Ps.36.12#t0005"
        }
      ],
      "footnotes": []
    }
  ]
}